<?xml version="1.0" encoding="utf-8" ?>
<Sports>
	<sport Sport="baseball">
		<League League="american">
			<Divisons>
				<division Division ="central">
					<team Team="White Sox">
						<player Player ="Tim Anderson" />
						<player Player ="Luis Robert" />
					</team>
					<team Team="Indians">
						<player Player ="Shane Bieber" />
						<player Player ="Josh Naylor" />
					</team>
					<team Team="Tigers">
						<player Player ="Eric Hease" />
						<player Player ="Casey Mize" />
					</team>
					<team Team="Twins">
						<player Player ="Max Kepler" />
						<player Player ="Alex Kirillof" />
					</team>
					<team Team="Royals">
						<player Player ="Whit Merrifi" />
						<player Player ="Brady Singer" />
					</team>
				</division>
				<division Division ="east">
					<team Team="Red Sox">
						<player Player ="Chris Sale" />
						<player Player ="Alex Verdugo" />
					</team>
					<team Team="Rays">
						<player Player ="Wander Franco" />
						<player Player ="Kevin Kiermaier" />
					</team>
					<team Team="Yankees">
						<player Player ="Gerrit Cole" />
						<player Player ="Rougned Odor" />
					</team>
					<team Team="Blue Jays">
						<player Player ="George Springer" />
						<player Player ="Bo Bichette" />
					</team>
					<team Team="Orioles">
						<player Player ="Trey Mancini" />
						<player Player ="Matt Harvey" />
					</team>
				</division>
				<division Division ="west">
					<team Team="Astros">
						<player Player ="Carlos Correa" />
						<player Player ="Justin Velander" />
					</team>
					<team Team="Athletics">
						<player Player ="Elvis Andrus" />
						<player Player ="Sean Manaea" />
					</team>
					<team Team="Mariners">
						<player Player ="Logan Gilbert" />
						<player Player ="Kyle Seager" />
					</team>
					<team Team="Angels">
						<player Player ="Mike Trout" />
						<player Player ="Jared Walsh" />
					</team>
					<team Team="Rangers">
						<player Player ="ArtemiPanarin" />
						<player Player ="Adam Fox" />
					</team>
				</division>
			</Divisons>
		</League>
		<League League="national">
			<Divisons>
				<division Division ="central">
					<team Team="Brewers">
						<player Player ="willy Adames" />
						<player Player ="Crobin Burnes" />
					</team>
					<team Team="Reds">
						<player Player ="Joey Votto" />
						<player Player ="Wade Miley" />
					</team>
					<team Team="Cardinals">
						<player Player ="Kyle Murray" />
						<player Player ="JJ Watt" />
					</team>
					<team Team="Cubs">
						<player Player ="Kris Bryant" />
						<player Player ="Jake Arrieta" />
					</team>
					<team Team="Pirates">
						<player Player ="Adam Frazier" />
						<player Player ="Bryan Reynolds" />
					</team>
				</division>
				<division Division ="east">
					<team Team="Mets">
						<player Player ="Jacob deGrom" />
						<player Player ="Pete Alonso" />
					</team>
					<team Team="Phillies">
						<player Player ="bryce harper" />
						<player Player ="alec bohm" />
					</team>
					<team Team="Braves">
						<player Player ="Marcell Ozuna" />
						<player Player ="Freddie Freeman" />
					</team>
					<team Team="Nationals">
						<player Player ="Juan solo" />
						<player Player ="Max Scherzer" />
					</team>
					<team Team="Marlins">
						<player Player ="Starling Marte" />
						<player Player ="Trevor Rog" />
					</team>
				</division>
				<division Division ="west">
					<team Team="Giants">
						<player Player ="Daniel Jones" />
						<player Player ="Kenny Golladay" />
					</team>
					<team Team="Dodgers">
						<player Player ="Trevor Bauer" />
						<player Player ="Mookie Betts" />
					</team>
					<team Team="Padres">
						<player Player ="yu Darvish" />
						<player Player ="Manny Machado" />
					</team>
					<team Team="Rockies">
						<player Player ="Charlie Blackmon" />
						<player Player ="Trevor Story" />
					</team>
					<team Team="Diamondbacks">
						<player Player ="Madison Bumgarner" />
						<player Player ="Ketel Matre" />
					</team>
				</division>
			</Divisons>
		</League>
	</sport>
</Sports>